sqlinjection/__init__.py
sqlinjection/errors.py
sqlinjection/sql_injection.py
sqlinjection-0.0.6.dist-info/METADATA
sqlinjection-0.0.6.dist-info/WHEEL
sqlinjection-0.0.6.dist-info/licenses/LICENSE
sqlinjection-0.0.6.dist-info/RECORD
