Metadata-Version: 2.3
Name: sqlinjection
Version: 0.0.6
Summary: Sql injection detector
Project-URL: Homepage, https://github.com/zenitaeglos/sqlinjection
Project-URL: Issues, https://github.com/zenitaeglos/sqlinjection/issues
Author-email: Alejandro Martinez <aegloszenit@protonmail.ch>
License-File: LICENSE
Classifier: License :: OSI Approved :: MIT License
Classifier: Operating System :: OS Independent
Classifier: Programming Language :: Python :: 3
Requires-Python: >=3.10
